dbeasy_py/__init__.py
dbeasy_py/dbeasy_py.py
dbeasy_py-0.1.dist-info/LICENCE
dbeasy_py-0.1.dist-info/METADATA
dbeasy_py-0.1.dist-info/WHEEL
dbeasy_py-0.1.dist-info/top_level.txt
dbeasy_py-0.1.dist-info/RECORD
