Metadata-Version: 2.1
Name: dbeasy-py
Version: 0.1
Summary: A package to facilitate the use of the database.
Home-page: https://github.com/brunowanderson7/dbeasy_py
Author: Bruno Wanderson
Author-email: brunowanderson8@gmail.com
Classifier: Programming Language :: Python :: 3
Classifier: License :: OSI Approved :: MIT License
Classifier: Operating System :: OS Independent
Requires-Python: >=3.8
License-File: LICENCE
